pyboost/__init__.py
pyboost/__main__.py
pyboost/backup.py
pyboost/core.py
pyboost/formatter.py
pyboost/rmcm.py
pyboost/utils.py
pyboost_toolkit-1.0.0.dist-info/licenses/LICENSE
tests/__init__.py
tests/test_backup.py
tests/test_core.py
tests/test_formatter.py
tests/test_rmcm.py
tests/test_utils.py
pyboost_toolkit-1.0.0.dist-info/METADATA
pyboost_toolkit-1.0.0.dist-info/WHEEL
pyboost_toolkit-1.0.0.dist-info/entry_points.txt
pyboost_toolkit-1.0.0.dist-info/top_level.txt
pyboost_toolkit-1.0.0.dist-info/RECORD
