Metadata-Version: 2.4
Name: pyboost-toolkit
Version: 1.0.0
Summary: Ultimate Python Code Maintenance Toolkit
Home-page: https://github.com/AlexandrosLiaskos/pyboost
Author: Alexandros Liaskos
Author-email: Alexandros Liaskos <alexandros.liaskos@gmail.com>
License-Expression: MIT
Project-URL: Documentation, https://github.com/AlexandrosLiaskos/pyboost/blob/main/README.md
Project-URL: Bug Reports, https://github.com/AlexandrosLiaskos/pyboost/issues
Project-URL: Source Code, https://github.com/AlexandrosLiaskos/pyboost
Classifier: Development Status :: 5 - Production/Stable
Classifier: Intended Audience :: Developers
Classifier: Programming Language :: Python :: 3
Classifier: Programming Language :: Python :: 3.8
Classifier: Programming Language :: Python :: 3.9
Classifier: Programming Language :: Python :: 3.10
Classifier: Programming Language :: Python :: 3.11
Classifier: Programming Language :: Python :: 3.12
Classifier: Topic :: Software Development :: Libraries :: Python Modules
Classifier: Topic :: Software Development :: Quality Assurance
Requires-Python: >=3.8
License-File: LICENSE
Requires-Dist: rich>=13.0.0
Provides-Extra: dev
Requires-Dist: pytest>=7.0.0; extra == "dev"
Requires-Dist: pytest-cov>=4.0.0; extra == "dev"
Requires-Dist: black>=23.0.0; extra == "dev"
Requires-Dist: isort>=5.0.0; extra == "dev"
Requires-Dist: mypy>=1.0.0; extra == "dev"
Provides-Extra: rmcm
Provides-Extra: all
Requires-Dist: autoflake>=2.0.0; extra == "all"
Requires-Dist: pyupgrade>=3.0.0; extra == "all"
Requires-Dist: isort>=5.0.0; extra == "all"
Requires-Dist: black>=23.0.0; extra == "all"
Requires-Dist: ruff>=0.0.1; extra == "all"
Requires-Dist: mypy>=1.0.0; extra == "all"
Requires-Dist: bandit>=1.0.0; extra == "all"
Requires-Dist: vulture>=2.0.0; extra == "all"
Requires-Dist: rich>=13.0.0; extra == "all"
Dynamic: author
Dynamic: classifier
Dynamic: home-page
Dynamic: license-file
Dynamic: project-url
Dynamic: provides-extra
Dynamic: requires-dist
Dynamic: requires-python
